data/__init__.py
data/kaomojis.yml
data/load_kaomojis.py
data/__pycache__/__init__.cpython-36.pyc
data/__pycache__/load_kaomojis.cpython-36.pyc
kaomoji/__init__.py
kaomoji/__main__.py
kaomoji/kaomoji.py
py_kaomoji-0.1.1.dist-info/DESCRIPTION.rst
py_kaomoji-0.1.1.dist-info/METADATA
py_kaomoji-0.1.1.dist-info/RECORD
py_kaomoji-0.1.1.dist-info/WHEEL
py_kaomoji-0.1.1.dist-info/entry_points.txt
py_kaomoji-0.1.1.dist-info/metadata.json
py_kaomoji-0.1.1.dist-info/top_level.txt
test/__init__.py
test/test_kaomoji.py
