Metadata-Version: 2.0
Name: py-kaomoji
Version: 0.1.1
Summary: Python Boilerplate contains all the boilerplate you need to create a Python package.
Home-page: https://github.com/shibuiwilliam/py-kaomoji
Author: Shibui Yusuke
Author-email: shibuiyusuke@gmail.com
License: UNKNOWN
Keywords: kaomoji
Platform: UNKNOWN
Classifier: Development Status :: 2 - Pre-Alpha
Classifier: Natural Language :: English
Classifier: License :: OSI Approved :: MIT License
Classifier: Programming Language :: Python :: 3.6
Classifier: Operating System :: OS Independent
